<package>
  <description brief="ocr_server">

     ocr_server

  </description>
  <author>Benjamin Pitzer</author>
  <license>BSD</license>
  <review status="unreviewed" notes=""/>
  <url>http://ros.org/wiki/ocr_server</url>

  <depend package="roscpp"/>
  <depend package="sensor_msgs"/>
  <depend package="opencv2"/>  
  <depend package="image_transport"/>
  <depend package="cv_bridge"/>
  <depend package="tesseract"/>
  
  <export>
    <cpp cflags="-I${prefix}/srv_gen/cpp"/>
  </export>


</package>


